nord_pygments.py
nord_pygments-0.0.3.dist-info/LICENSE
nord_pygments-0.0.3.dist-info/METADATA
nord_pygments-0.0.3.dist-info/WHEEL
nord_pygments-0.0.3.dist-info/entry_points.txt
nord_pygments-0.0.3.dist-info/top_level.txt
nord_pygments-0.0.3.dist-info/RECORD
